cleanvision/__init__.py
cleanvision/imagelab.py
cleanvision/py.typed
cleanvision/dataset/__init__.py
cleanvision/dataset/base_dataset.py
cleanvision/dataset/fsspec_dataset.py
cleanvision/dataset/hf_dataset.py
cleanvision/dataset/torch_dataset.py
cleanvision/dataset/utils.py
cleanvision/issue_managers/__init__.py
cleanvision/issue_managers/duplicate_issue_manager.py
cleanvision/issue_managers/image_property.py
cleanvision/issue_managers/image_property_issue_manager.py
cleanvision/utils/__init__.py
cleanvision/utils/base_issue_manager.py
cleanvision/utils/constants.py
cleanvision/utils/serialize.py
cleanvision/utils/utils.py
cleanvision/utils/viz_manager.py
cleanvision-0.3.7.dist-info/licenses/LICENSE
cleanvision-0.3.7.dist-info/METADATA
cleanvision-0.3.7.dist-info/WHEEL
cleanvision-0.3.7.dist-info/top_level.txt
cleanvision-0.3.7.dist-info/RECORD
