Metadata-Version: 2.4
Name: cleanvision
Version: 0.3.7
Summary: Find issues in image datasets
Author-email: "Cleanlab Inc." <team@cleanlab.ai>
License-Expression: Apache-2.0
Project-URL: Source, https://github.com/cleanlab/cleanvision
Project-URL: Bug Tracker, https://github.com/cleanlab/cleanvision/issues
Project-URL: Documentation, https://cleanvision.readthedocs.io/
Keywords: computer_vision,cv,image_data,issue_detection,data_quality,image_quality,machine_learning,data_cleaning,image_deduplication
Classifier: Programming Language :: Python :: 3
Classifier: Programming Language :: Python :: 3.7
Classifier: Programming Language :: Python :: 3.8
Classifier: Programming Language :: Python :: 3.9
Classifier: Programming Language :: Python :: 3.10
Classifier: Programming Language :: Python :: 3.11
Classifier: Programming Language :: Python
Classifier: Topic :: Software Development
Classifier: Topic :: Scientific/Engineering
Classifier: Topic :: Scientific/Engineering :: Mathematics
Classifier: Topic :: Scientific/Engineering :: Artificial Intelligence
Classifier: Topic :: Software Development :: Libraries
Classifier: Topic :: Software Development :: Libraries :: Python Modules
Requires-Python: >=3.7
License-File: LICENSE
Requires-Dist: Pillow>=9.3
Requires-Dist: numpy>=1.20.0
Requires-Dist: pandas>=1.1.5
Requires-Dist: tabulate>=0.8.3
Requires-Dist: imagehash>=4.2.0
Requires-Dist: tqdm>=4.53.0
Requires-Dist: matplotlib>=3.4
Requires-Dist: fsspec>=2023.1.0
Provides-Extra: huggingface
Requires-Dist: datasets>=2.15.0; python_version > "3.7" and extra == "huggingface"
Requires-Dist: datasets>=2.7.0; python_version < "3.8" and extra == "huggingface"
Provides-Extra: pytorch
Requires-Dist: torchvision>=0.12.0; extra == "pytorch"
Provides-Extra: azure
Requires-Dist: adlfs>=2022.2.0; extra == "azure"
Provides-Extra: gcs
Requires-Dist: gcsfs>=2022.1.0; extra == "gcs"
Provides-Extra: s3
Requires-Dist: s3fs>=2023.1.0; extra == "s3"
Provides-Extra: all
Requires-Dist: cleanvision[azure,gcs,huggingface,pytorch,s3]; extra == "all"
Dynamic: license-file
